screens/__init__.py
screens/exceptions.py
screens/req.py
screens/screens.py
screens/units.py
screens_py-0.5.0.post2.dist-info/LICENSE
screens_py-0.5.0.post2.dist-info/METADATA
screens_py-0.5.0.post2.dist-info/WHEEL
screens_py-0.5.0.post2.dist-info/RECORD
