Metadata-Version: 2.1
Name: screens-py
Version: 0.5.0.post2
Summary: A light-weight library for easy interaction between Python and GNU screen.
License: GNU GENERAL PUBLIC
Author: Romani
Author-email: semina054@gmail.com
Requires-Python: >=3.9,<4.0
Classifier: License :: Other/Proprietary License
Classifier: Programming Language :: Python :: 3
Classifier: Programming Language :: Python :: 3.9
Classifier: Programming Language :: Python :: 3.10
Classifier: Programming Language :: Python :: 3.11
Requires-Dist: psutil (>=5.9.5,<6.0.0)
Requires-Dist: vbml (>=1.1.post1,<2.0)
